cloud_storage_slim/__init__.py
cloud_storage_slim/alibaba_cloud_oss.py
cloud_storage_slim/amazon_s3.py
cloud_storage_slim/azure_storage.py
cloud_storage_slim/byteplus_torch_object_storage.py
cloud_storage_slim/google_cloud_storage.py
cloud_storage_slim/http_client.py
cloud_storage_slim/utils.py
cloud_storage_slim-0.3.5.dist-info/METADATA
cloud_storage_slim-0.3.5.dist-info/WHEEL
cloud_storage_slim-0.3.5.dist-info/top_level.txt
cloud_storage_slim-0.3.5.dist-info/RECORD
