Metadata-Version: 2.1
Name: cloud_storage_slim
Version: 0.3.5
Summary: A lightweight cloud storage package for popular cloud storage services.
Home-page: https://github.com/yingca1/cloud-storage-slim
Author: Ying Cai
Author-email: i@caiying.me
